fabricasdk/Contract.py
fabricasdk/EthereumClient.py
fabricasdk/FabricaApiClient.py
fabricasdk/State.py
fabricasdk/__init__.py
fabricasdk/contracts/FabricaMultisigFactory.py
fabricasdk/contracts/FabricaMultisigWallet.py
fabricasdk/contracts/FabricaToken.py
fabricasdk/resources/blockchain/fabrica-multisig-factory/abi.json
fabricasdk/resources/blockchain/fabrica-multisig-factory/bytecode.json
fabricasdk/resources/blockchain/fabrica-multisig-factory/networks.json
fabricasdk/resources/blockchain/fabrica-multisig-wallet/abi.json
fabricasdk/resources/blockchain/fabrica-token/abi.json
fabricasdk/resources/blockchain/fabrica-token/bytecode.json
fabricasdk/resources/blockchain/fabrica-token/networks.json
fabricasdk-0.2.0.dist-info/LICENSE
fabricasdk-0.2.0.dist-info/METADATA
fabricasdk-0.2.0.dist-info/WHEEL
fabricasdk-0.2.0.dist-info/top_level.txt
fabricasdk-0.2.0.dist-info/RECORD
