Metadata-Version: 2.1
Name: fabricasdk
Version: 0.2.0
Summary: fabrica sdk
Home-page: UNKNOWN
Author: Fabrica Inc.
Author-email: info@fabrica.city
License: UNKNOWN
Platform: UNKNOWN
Requires-Dist: ecdsa (==0.13)
Requires-Dist: ipfsapi (==0.4.3)
Requires-Dist: requests (==2.19.1)
Requires-Dist: rfc3986 (==1.1.0)
Requires-Dist: web3 (==4.6.0)
